Workbook

Sheet Findings Register
A1: ID | B1: Severity | C1: Section | D1: Finding | E1: Location (file:line) | F1: Impact | G1: Recommended fix | H1: Effort | I1: Stage | J1: Status | K1: Owner | L1: Target date | M1: Verified | N1: Notes
A2: P0-01 | B2: P0 | C2: 9 Security | D2: Live Telegram token public in git history (.env, 6 trees) and in HEAD (data/logs/system.log) | E2: 7dd9527 .env; data/logs/system.log:147 | F2: Attacker can setWebhook to seize the command channel silently (losing /panic), impersonate the bot to the operator, and read commands. Repo is public despite its name. | G2: Rotate token -> deleteWebhook -> repo private -> untrack artifacts -> git filter-repo. Add log redaction filter. | H2: 2 h | I2: A | J2: Open | M2: No
A3: ARCH-01 | B3: Critical | C3: 2 Architecture | D3: No idempotency key on any order; timeout-then-retry can double-fill | E3: bridge_zmq.py:70; system_controller.py:449 | F3: REQ timeout returns False while the order may be live. magic is a shared constant 88000; only the broker generates a unique ID, after the fill. Neither side can recognise a retry. | G3: UUID per intent hashed into `comment`; EA-side dedup; on timeout QUERY state, never resend. | H3: 2 d | I3: B | J3: Open | M3: No
A4: ARCH-02 | B4: Critical | C4: 2 Architecture | D4: Bridge protocol has no schema, no version, no sequence numbers | E4: bridge_zmq.py:57; CLAUDE.md:37 | F4: Untyped dicts both sides. A field rename in Python plus a stale EA binary (manual MetaEditor recompile) disagree silently. | G4: Versioned message schema validated at the boundary on both sides. | H4: 2 d | I4: B | J4: Open | M4: No
A5: OBS-01 | B5: Critical | C5: 7 Observability | D5: Journal schema cannot validate the live ratchet; soak data accruing now is unusable | E5: state_manager.py:66,200-205 | F5: No exit reason, no ratchet level at exit, no slippage, no submit/fill timestamps, no commission/swap, no equity snapshot. time_placed and ratchet_level exist in active_orders and are explicitly not copied by archive_trade. DEADLINE-SENSITIVE: closed trades cannot be re-recorded. | G5: Add columns + a trade_events table appending one row per MODIFY/partial with the heartbeat-observed outcome. | H5: 1 d | I5: B | J5: Open | M5: No
A6: RISK-01 | B6: Critical | C6: 3 Risk | D6: Daily drawdown anchor resets on every process restart; no restart cap | E6: risk_manager.py:51; titan-live.service:29 | F6: day_start_equity is in-memory, re-anchored on the first heartbeat. Restart=on-failure with no StartLimitBurst. Expected loss is 3% x crash count, unbounded, in one day. | G6: Persist day_start_equity + date to SQLite; restore on boot. Add StartLimitBurst=3, StartLimitIntervalSec=300. | H6: 2 h | I6: A | J6: Open | M6: No
A7: RISK-02 | B7: Critical | C7: 3 Risk | D7: Position-count and per-symbol caps are blind to resting pending orders | E7: exposure.py:92,100; arbiter.py:250 | F7: Both gates receive only filled positions. The only live strategy enters on LIMIT and limits rest up to 12 bars. Caps are unenforced in the book's normal state; only the 5% aggregate cap bites, and it permits 5 commitments on one symbol in one direction. | G7: Pass current_pending_orders into check_exposure and arbiter._apply_caps. | H7: 1 h | I7: A | J7: Open | M7: No
A8: RISK-10 | B8: Critical | C8: 3 Risk | D8: Live bars and history bars are timestamped in two different timezones, in the same buffer | E8: candle_maker.py:113; data_store.py:79 | F8: History via pd.to_datetime(unit='s') = server time; live via datetime.fromtimestamp() = local time. On a UTC+3 host every live bar is 3h displaced. ATR, FVG and swing detection compute across the discontinuity. Invisible on a UTC host. | G8: datetime.fromtimestamp(ts, tz=utc).replace(tzinfo=None). | H8: 1 h | I8: A | J8: Open | M8: No
A9: SEC-05 | B9: Critical | C9: 9 Security | D9: ZMQ unauthenticated, bound tcp://*, inbound messages never validated | E9: bridge_zmq.py:25,36,53; risk_manager.py:62; TitanZmq.mqh | F9: One poisoned HISTORY message sets every trade to hard_max_lots (5.00). Fabricated HEARTBEAT defeats the drawdown breaker and wipes the position view. A PULL peer on :32768 steals half of all MODIFY/CLOSE/CANCEL. Identical damage from a broker misquote, no attacker required. | G9: Bounds-check update_symbol_specs; bind the specific interface (config already declares host); HMAC every message. | H9: 2 h | I9: A | J9: Open | M9: No
A10: STRAT-01 | B10: Critical | C10: 6 Strategy | D10: Validated exit engine is not the live exit engine; the edge lives entirely in exits | E10: poc_sb_stops.py:215 vs trade_manager.py:51 | F10: Strategy is -0.122R with fixed exits, +0.194R with ratchet+runner. The validated ratchet is an offline reimplementation; research_run.py has zero ratchet references. Live expectancy is unmeasured and the sign is not guaranteed. | G10: Extract the ratchet to one pure function; call from TradeManager and research_run; delete replay_managed; re-run the study. | H10: 2 d | I10: B | J10: Open | M10: No
A11: ARCH-04 | B11: High | C11: 2 Architecture | D11: ZMQ bind failures are non-fatal; bot boots with a dead socket | E11: bridge_zmq.py:26,37,54; :781 | F11: Port held by a stray process or a second instance -> prints, continues, _boot_sequence returns True, hangs forever in _wait_for_bridge_connection. | G11: Raise on bind failure. | H11: 15 m | I11: A | J11: Open | M11: No
A12: ARCH-05 | B12: High | C12: 2 Architecture | D12: Weak ack; no nack taxonomy; no retry policy at all | E12: bridge_zmq.py:75; system_controller.py:472 | F12: Requote, rejection, insufficient margin and invalid stops all collapse into False. A transient failure is a permanently missed trade, indistinguishable from a permanent rejection. | G12: Reason codes in the reply; retry requotes only; alert on rejects. | H12: 1 d | I12: C | J12: Open | M12: No
A13: ARCH-06 | B13: High | C13: 2 Architecture | D13: No single-instance lock; two bots can write the same databases | E13: NOT FOUND in src/; tradebot/core/recovery.py:147 | F13: Instance 2 cannot trade (dead sockets) but does open and can write both SQLite DBs. | G13: Port recovery.acquire_boot_lock into main.py. | H13: 30 m | I13: A | J13: Open | M13: No
... A102: STRAT-08 | B102: Low | C102: 6 Strategy | D102: Backtest shift_hours=-7 is fragile across misaligned DST transitions | E102: backtest_engine.py:221 | F102: Coincidentally correct year-round for an EET/EEST broker into EST/EDT, wrong for the ~3 weeks each year when the transitions do not align. | G102: Use pytz conversion. | H102: 1 h | I102: C | J102: Open | M102: No

Sheet Summary
A1: TITAN AUDIT — FINDINGS SUMMARY
A2: Repository: Kiyingijmc/Titanprivate- | Commits 7dd9527..cc59155 | Audit date 2026-07-30
A3: Counts are live formulas over the 'Findings Register' sheet — they update as you set Status.
A5: BY SEVERITY
A6: Severity | B6: Total | C6: Open | D6: Fixed/Verified | E6: % closed
A7: P0 | B7: =COUNTIF('Findings Register'!$B$2:$B$102,$A7) -> 1 | C7: =COUNTIFS('Findings Register'!$B$2:$B$102,$A7,'Findings Register'!$J$2:$J$102,"Open") -> 1 | D7: =COUNTIFS('Findings Register'!$B$2:$B$102,$A7,'Findings Register'!$J$2:$J$102,"Fixed")+COUNTIFS('Findings Register'!$B$2:$B$102,$A7,'Findings Register'!$J$2:$J$102,"Verified") -> 0 | E7: =IF($B7=0,0,$D7/$B7) -> 0
A8: Critical | B8: =COUNTIF('Findings Register'!$B$2:$B$102,$A8) -> 8 | C8: =COUNTIFS('Findings Register'!$B$2:$B$102,$A8,'Findings Register'!$J$2:$J$102,"Open") -> 8 | D8: =COUNTIFS('Findings Register'!$B$2:$B$102,$A8,'Findings Register'!$J$2:$J$102,"Fixed")+COUNTIFS('Findings Register'!$B$2:$B$102,$A8,'Findings Register'!$J$2:$J$102,"Verified") -> 0 | E8: =IF($B8=0,0,$D8/$B8) -> 0
A9: High | B9: =COUNTIF('Findings Register'!$B$2:$B$102,$A9) -> 36 | C9: =COUNTIFS('Findings Register'!$B$2:$B$102,$A9,'Findings Register'!$J$2:$J$102,"Open") -> 36 | D9: =COUNTIFS('Findings Register'!$B$2:$B$102,$A9,'Findings Register'!$J$2:$J$102,"Fixed")+COUNTIFS('Findings Register'!$B$2:$B$102,$A9,'Findings Register'!$J$2:$J$102,"Verified") -> 0 | E9: =IF($B9=0,0,$D9/$B9) -> 0
A10: Medium | B10: =COUNTIF('Findings Register'!$B$2:$B$102,$A10) -> 39 | C10: =COUNTIFS('Findings Register'!$B$2:$B$102,$A10,'Findings Register'!$J$2:$J$102,"Open") -> 39 | D10: =COUNTIFS('Findings Register'!$B$2:$B$102,$A10,'Findings Register'!$J$2:$J$102,"Fixed")+COUNTIFS('Findings Register'!$B$2:$B$102,$A10,'Findings Register'!$J$2:$J$102,"Verified") -> 0 | E10: =IF($B10=0,0,$D10/$B10) -> 0
A11: Low | B11: =COUNTIF('Findings Register'!$B$2:$B$102,$A11) -> 17 | C11: =COUNTIFS('Findings Register'!$B$2:$B$102,$A11,'Findings Register'!$J$2:$J$102,"Open") -> 17 | D11: =COUNTIFS('Findings Register'!$B$2:$B$102,$A11,'Findings Register'!$J$2:$J$102,"Fixed")+COUNTIFS('Findings Register'!$B$2:$B$102,$A11,'Findings Register'!$J$2:$J$102,"Verified") -> 0 | E11: =IF($B11=0,0,$D11/$B11) -> 0
A12: TOTAL | B12: =SUM(B7:B11) -> 101 | C12: =SUM(C7:C11) -> 101 | D12: =SUM(D7:D11) -> 0 | E12: =IF($B12=0,0,$D12/$B12) -> 0
A14: BY SECTION
A15: Section | B15: Total | C15: Open
A16: 10 Operations | B16: =COUNTIF('Findings Register'!$C$2:$C$102,$A16) -> 17 | C16: =COUNTIFS('Findings Register'!$C$2:$C$102,$A16,'Findings Register'!$J$2:$J$102,"Open") -> 17
A17: 2 Architecture | B17: =COUNTIF('Findings Register'!$C$2:$C$102,$A17) -> 11 | C17: =COUNTIFS('Findings Register'!$C$2:$C$102,$A17,'Findings Register'!$J$2:$J$102,"Open") -> 11
A18: 3 Risk | B18: =COUNTIF('Findings Register'!$C$2:$C$102,$A18) -> 15 | C18: =COUNTIFS('Findings Register'!$C$2:$C$102,$A18,'Findings Register'!$J$2:$J$102,"Open") -> 15
A19: 4 Entries/Exits | B19: =COUNTIF('Findings Register'!$C$2:$C$102,$A19) -> 9 | C19: =COUNTIFS('Findings Register'!$C$2:$C$102,$A19,'Findings Register'!$J$2:$J$102,"Open") -> 9
A20: 5 Execution | B20: =COUNTIF('Findings Register'!$C$2:$C$102,$A20) -> 9 | C20: =COUNTIFS('Findings Register'!$C$2:$C$102,$A20,'Findings Register'!$J$2:$J$102,"Open") -> 9
A21: 6 Strategy | B21: =COUNTIF('Findings Register'!$C$2:$C$102,$A21) -> 8 | C21: =COUNTIFS('Findings Register'!$C$2:$C$102,$A21,'Findings Register'!$J$2:$J$102,"Open") -> 8
A22: 7 Observability | B22: =COUNTIF('Findings Register'!$C$2:$C$102,$A22) -> 12 | C22: =COUNTIFS('Findings Register'!$C$2:$C$102,$A22,'Findings Register'!$J$2:$J$102,"Open") -> 12
A23: 8 Control | B23: =COUNTIF('Findings Register'!$C$2:$C$102,$A23) -> 10 | C23: =COUNTIFS('Findings Register'!$C$2:$C$102,$A23,'Findings Register'!$J$2:$J$102,"Open") -> 10
A24: 9 Security | B24: =COUNTIF('Findings Register'!$C$2:$C$102,$A24) -> 10 | C24: =COUNTIFS('Findings Register'!$C$2:$C$102,$A24,'Findings Register'!$J$2:$J$102,"Open") -> 10
A26: BY REMEDIATION STAGE
A27: Stage | B27: Meaning | C27: Total | D27: Open
A28: A | B28: Stop the bleeding — before ANY run, demo included (~1 week) | C28: =COUNTIF('Findings Register'!$I$2:$I$102,$A28) -> 36 | D28: =COUNTIFS('Findings Register'!$I$2:$I$102,$A28,'Findings Register'!$J$2:$J$102,"Open") -> 36
A29: B | B29: Foundations — before live capital (~3 weeks) | C29: =COUNTIF('Findings Register'!$I$2:$I$102,$A29) -> 41 | D29: =COUNTIFS('Findings Register'!$I$2:$I$102,$A29,'Findings Register'!$J$2:$J$102,"Open") -> 41
A30: C | B30: Feature completion — during and after the soak (~3 weeks) | C30: =COUNTIF('Findings Register'!$I$2:$I$102,$A30) -> 24 | D30: =COUNTIFS('Findings Register'!$I$2:$I$102,$A30,'Findings Register'!$J$2:$J$102,"Open") -> 24

Sheet Top 10 by Expected Cost
A1: TOP 10 FINDINGS — ranked by expected financial impact x likelihood
A2: Ranking is a judgement, not a formula. It answers: what should I fix first if I could only fix ten things?
A4: Rank | B4: ID | C4: Finding | D4: Impact if it fires | E4: Likelihood | F4: One-line fix
A5: 1 | B5: P0-01 | C5: Live Telegram token public in two places on a public repo | D5: High — loss of control channel + impersonation during an incident | E5: CERTAIN — already happened | F5: Rotate -> deleteWebhook -> private -> filter-repo
A6: 2 | B6: RISK-01 | C6: Daily drawdown anchor resets on every restart; no restart cap | D6: VERY HIGH — 3% x crash count, unbounded, in one day | E6: High — several crash paths exist | F6: Persist anchor + date; StartLimitBurst=3
A7: 3 | B7: STRAT-01 | C7: Live expectancy is unmeasured (validated exits != live exits) | D7: VERY HIGH — may be running a negative-expectancy system | E7: CERTAIN — current state | F7: Extract the ratchet to one function; re-run the study
A8: 4 | B8: RISK-02 | C8: Count and per-symbol caps blind to resting limit orders | D8: High — 5% concentrated vs 1% intended | E8: High — the book's normal state, weekly | F8: Pass pendings into both count gates
A9: 5 | B9: SEC-05 | C9: One ZMQ message re-sizes every trade to 5.00 lots | D9: CATASTROPHIC — ~100x intended risk | E9: Moderate adversarially; the broker-misquote variant is plausible | F9: Bounds-check specs; bind specific interface; HMAC
A10: 6 | B10: RISK-10 | C10: Live and history bars timestamped in different timezones | D10: High — every indicator computed across a discontinuity | E10: CERTAIN on the deployment host | F10: fromtimestamp(ts, tz=utc)
A11: 7 | B11: CTRL-02 | C11: Flatten commands report unverified success | D11: UNBOUNDED — operator stands down believing they are flat | E11: Moderate | F11: Report observed position count after 2 heartbeats
A12: 8 | B12: ARCH-01 | C12: No idempotency key on any order | D12: High — duplicate fills, under-counted book risk | E12: Moderate — 2.5s timeout on a single-threaded EA | F12: UUID in comment; EA dedup; query, never resend
A13: 9 | B13: OBS-01 | C13: Journal cannot validate the ratchet | D13: High (indirect) — keeps #3 open indefinitely | E13: CERTAIN, and deadline-sensitive | F13: Add columns + trade_events table BEFORE the soak continues
A14: 10 | B14: OPS-01 | C14: No demo/live safeguard of any kind | D14: CATASTROPHIC — full live exposure from an unvalidated run | E14: Low-moderate — one EA misconfiguration | F14: EA reports trade mode; Python refuses on mismatch

Sheet Legend
A1: HOW TO USE THIS REGISTER
A3: Editable columns | B3: Only J (Status), K (Owner), L (Target date), M (Verified) and N (Notes) are yours to fill in.
B4: Columns A-I are audit output. Changing them breaks the Summary formulas.
A6: Status values | B6: Open · In progress · Fixed · Verified · Deferred · Won't fix (dropdown)
B7: 'Fixed' means the code changed. 'Verified' means you proved it with a test or an observation.
B8: Do not mark a risk finding Verified without a test that fails on the old code.
A10: Severity | B10: P0 — act today. A live credential is public.
B11: Critical — blocks live capital. Can cause loss far outside the intended risk profile.
B12: High — blocks live capital. Serious, but bounded or requiring a trigger.
B13: Medium — fix before scaling. Correctness, realism or hygiene.
B14: Low — hygiene. Stale docs, naming, missing metrics, unused mechanisms.
A16: Stage | B16: A — Stop the bleeding. Before ANY run, demo included. ~1 week.
B17: B — Foundations. Before live capital. ~3 weeks.
B18: C — Feature completion. During and after the soak. ~3 weeks.
A20: Location | B20: file:line references point into commits 7dd9527..cc59155.
B21: 'NOT FOUND' means searched for and absent — a finding, not an omission.
A23: Sequencing note | B23: OBS-01 (journal schema) has a DEADLINE the others do not: every day the demo soak
B24: runs against the current schema is a day of evidence that cannot be recovered.
B25: Do it first, then RISK-01 and RISK-02 the same day, then start the soak clock.
A27: Corrections | B27: Three findings were corrected during the audit and are recorded in 00-README-INDEX.md:
B28: the threading model (withdrawn), cached risk scalars (downgraded to Low), and the
B29: universe expansion (suspicion was wrong — it was properly re-validated).
